pimsviewer/__init__.py
pimsviewer/dimension.py
pimsviewer/dimension.ui
pimsviewer/example_plugins.py
pimsviewer/gui.py
pimsviewer/imagewidget.py
pimsviewer/mainwindow.ui
pimsviewer/pims_image.py
pimsviewer/plugins.py
pimsviewer/scroll_message_box.py
pimsviewer/utils.py
pimsviewer/wrapped_reader.py
pimsviewer-2.0.dist-info/LICENSE
pimsviewer-2.0.dist-info/METADATA
pimsviewer-2.0.dist-info/WHEEL
pimsviewer-2.0.dist-info/entry_points.txt
pimsviewer-2.0.dist-info/top_level.txt
pimsviewer-2.0.dist-info/RECORD
