Metadata-Version: 2.1
Name: pimsviewer
Version: 2.0
Summary: Viewer for Python IMage Sequence (PIMS).
Home-page: https://github.com/soft-matter/pimsviewer
Author: Ruben Verweij
Author-email: ruben@lighthacking.nl
License: UNKNOWN
Platform: UNKNOWN
Requires-Python: >=3.0
Requires-Dist: click
Requires-Dist: pims
Requires-Dist: PyQt5 (>=5.13.1)
Requires-Dist: pandas
Requires-Dist: numpy
Requires-Dist: Pillow
